tagsyncer/__init__.py
tagsyncer/tag_syncer.py
tagsyncer-1.0.dist-info/METADATA
tagsyncer-1.0.dist-info/RECORD
tagsyncer-1.0.dist-info/WHEEL
tagsyncer-1.0.dist-info/entry_points.txt
tagsyncer-1.0.dist-info/top_level.txt
