Metadata-Version: 2.1
Name: tagsyncer
Version: 1.0
Summary: Command line tool that syncs up ec2 instance tags with its ASG tags 
Home-page: https://github.com/SManral/tagsyncer.git
Author: Smriti Manral
Author-email: smriti.manral@gmail.com
License: MIT
Platform: UNKNOWN
Requires-Dist: boto3 (>=1.9.75)
Requires-Dist: logging (>=0.4.9.6)
